{"code":"10000","charge":true,"remain":19570,"msg":"查询成功,扣费","result":{"status":0,"msg":"ok","result":{"city":"KMG","endcity":"HET","date":"2022-04-15","list":[{"flightno":"A67127","airline":false,"realflightno":"","departportcode":"KMG","departport":"昆明长水国际机场","arrivalportcode":"HET","arrivalport":"白塔国际机场","departterminal":"","arrivalterminal":"","departdate":"2022-04-15","arrivaldate":"2022-04-15","departtime":"10:15","arrivaltime":"17:20","departdateadd":0,"arrivaldateadd":0,"craft":"32D","stopnum":"1","costtime":"7:05","punctualrate":"95","pricelist":[{"cabinname":"经济舱","cabincode":"Y","price":"2400","discount":"100"},{"cabinname":"经济舱","cabincode":"B","price":"2160","discount":"90"},{"cabinname":"经济舱","cabincode":"H","price":"1920","discount":"80"},{"cabinname":"经济舱","cabincode":"N","price":"1680","discount":"70"},{"cabinname":"经济舱","cabincode":"T","price":"1440","discount":"60"}],"minprice":"2400","airporttax":"50","fueltax":"100","food":0,"isasr":1,"iseticket":1,"iscodeshare":0}]}},"requestId":"c87a8e4866da42a1ab2e3f9e30748fd5"}